{
  "posts": [
    {
      "id": "1",
      "title": "a title",
      "views": 100
    },
    {
      "id": "2",
      "title": "another title",
      "views": 200
    }
  ],
  "comments": [
    {
      "id": "b44c",
      "text": "erez",
      "postId": "erez"
    },
    {
      "id": "d536",
      "text": "erez",
      "postId": "erez"
    },
    {
      "id": "9aec",
      "text": "erez",
      "postId": "erez"
    },
    {
      "id": "d72f",
      "text": "erez",
      "postId": "erez"
    },
    {
      "id": "8e22",
      "text": "erez",
      "postId": "erez"
    },
    {
      "id": "da12",
      "text": "erez",
      "postId": "erez"
    },
    {
      "id": "27f2",
      "text": "erez",
      "postId": "erez"
    },
    {
      "id": "dc1a",
      "text": "erez",
      "postId": "erez"
    },
    {
      "id": "138d",
      "text": "erez",
      "postId": "erez"
    },
    {
      "id": "0d77",
      "text": "erez",
      "postId": "erez"
    },
    {
      "id": "5783",
      "text": "erez",
      "postId": "erez"
    },
    {
      "id": "00c5",
      "text": "erez",
      "postId": "erez"
    },
    {
      "id": "4da2",
      "text": "erez",
      "postId": "erez"
    },
    {
      "id": "4e2d",
      "text": "erez",
      "postId": "erez"
    },
    {
      "id": "b96d",
      "text": "erez",
      "postId": "erez"
    },
    {
      "id": "ca65",
      "text": "erez",
      "postId": "erez"
    },
    {
      "id": "f1e8",
      "text": "erez",
      "postId": "erez"
    },
    {
      "id": "16ce",
      "text": "erez",
      "postId": "erez"
    },
    {
      "id": "a2d6",
      "text": "erez",
      "postId": "erez"
    },
    {
      "id": "68b6",
      "text": "erez",
      "postId": "erez"
    },
    {
      "id": "7f49",
      "text": "erez",
      "postId": "erez"
    },
    {
      "id": "d47c",
      "text": "erez",
      "postId": "erez"
    },
    {
      "id": "3a76",
      "text": "erez",
      "postId": "erez"
    },
    {
      "id": "b994",
      "text": "erez",
      "postId": "erez"
    },
    {
      "id": "f4b5",
      "text": "erez",
      "postId": "erez"
    },
    {
      "id": "bd34",
      "text": "erez",
      "postId": "erez"
    },
    {
      "id": "e2a8",
      "text": "erez",
      "postId": "erez"
    }
  ],
  "profile": {
    "name": "typicode"
  }
}